minio_hung/ReadMinio.py
minio_hung/__init__.py
Minio_hung-0.0.7.1.dist-info/LICENSE
Minio_hung-0.0.7.1.dist-info/METADATA
Minio_hung-0.0.7.1.dist-info/WHEEL
Minio_hung-0.0.7.1.dist-info/top_level.txt
Minio_hung-0.0.7.1.dist-info/RECORD
