Metadata-Version: 2.1
Name: Minio-hung
Version: 0.0.7.1
Summary: Makes you use Minio easier.
Home-page: https://github.com/lyduchung2001/Minio
Author: Ly Duc Hung
Author-email: lyduchung2001@gmail.com
Classifier: Programming Language :: Python :: 3
Classifier: License :: OSI Approved :: MIT License
Classifier: Operating System :: OS Independent
Requires-Python: >=3.6
License-File: LICENSE
Requires-Dist: numpy (==1.21.6)
Requires-Dist: pandas (==1.3.5)
Requires-Dist: minio (==7.1.9)
Requires-Dist: mysql-connector-python (==8.0.29)
Requires-Dist: python-cassandra (==0.6.1)
Requires-Dist: psycopg2
Requires-Dist: openpyxl (==3.0.10)
